yatta/__init__.py
yatta/client.py
yatta/enums.py
yatta/exceptions.py
yatta/utils.py
yatta/models/__init__.py
yatta/models/base.py
yatta/models/book.py
yatta/models/change_log.py
yatta/models/character.py
yatta/models/item.py
yatta/models/light_cone.py
yatta/models/message.py
yatta/models/relic.py
yatta_py-1.3.13.dist-info/METADATA
yatta_py-1.3.13.dist-info/WHEEL
yatta_py-1.3.13.dist-info/licenses/LICENSE
yatta_py-1.3.13.dist-info/RECORD
